{"success":true,"message":"","tablesdata":[{"tablename":"uidgen","values":[{"activeflg":1,"clientid":2,"code":"tcs_icc","deleteflg":0,"difftypeid":6,"id":1,"ifixsysid":"2a1e7653-7611-476c-bb7c-e8703eaf83c4","lastupdatedby":null,"lastupdateddate":"2022-01-16 17:02:15","mstorgnhirarchyid":2,"uid":10800},{"activeflg":1,"clientid":2,"code":null,"deleteflg":0,"difftypeid":43,"id":2,"ifixsysid":"fa39430a-d3cc-4a3d-926d-2a26d243553b","lastupdatedby":null,"lastupdateddate":"2022-01-16 17:02:15","mstorgnhirarchyid":2,"uid":750214},{"activeflg":1,"clientid":2,"code":"landmark","deleteflg":0,"difftypeid":6,"id":3,"ifixsysid":"e60a0fd4-e395-4c2d-b460-01ee4c932fe3","lastupdatedby":null,"lastupdateddate":"2022-01-16 17:02:15","mstorgnhirarchyid":7,"uid":26},{"activeflg":1,"clientid":2,"code":"ghj","deleteflg":0,"difftypeid":6,"id":4,"ifixsysid":"8c569ba3-d5ca-40a3-9ada-ba1bea82e7e4","lastupdatedby":null,"lastupdateddate":"2022-01-16 17:02:15","mstorgnhirarchyid":6,"uid":5},{"activeflg":1,"clientid":2,"code":"cial","deleteflg":0,"difftypeid":6,"id":5,"ifixsysid":"13cceed5-7d85-4e91-ad02-c527328f403c","lastupdatedby":null,"lastupdateddate":"2022-01-16 17:02:15","mstorgnhirarchyid":8,"uid":201},{"activeflg":1,"clientid":2,"code":"delphi-tvs","deleteflg":0,"difftypeid":6,"id":6,"ifixsysid":"7670fe2d-e149-47f7-b77b-ca96fc71cf9a","lastupdatedby":null,"lastupdateddate":"2022-01-16 17:02:15","mstorgnhirarchyid":9,"uid":27},{"activeflg":1,"clientid":2,"code":"marsh","deleteflg":0,"difftypeid":6,"id":7,"ifixsysid":"f1e1c327-c09c-4d72-a053-cada34287089","lastupdatedby":null,"lastupdateddate":"2022-01-16 17:02:15","mstorgnhirarchyid":10,"uid":155},{"activeflg":1,"clientid":2,"code":"ndb","deleteflg":0,"difftypeid":6,"id":8,"ifixsysid":"866d627c-e184-4b27-8152-956ab6e77c22","lastupdatedby":null,"lastupdateddate":"2022-01-16 17:02:15","mstorgnhirarchyid":11,"uid":24},{"activeflg":1,"clientid":2,"code":"tatasteel","deleteflg":0,"difftypeid":6,"id":9,"ifixsysid":"6905a9c4-bbd0-41f6-b6ad-bf5c8f607b18","lastupdatedby":null,"lastupdateddate":"2022-01-16 17:02:15","mstorgnhirarchyid":12,"uid":14}]}]}